lee1_mcp_demo/__init__.py
lee1_mcp_demo-0.1.0.dist-info/METADATA
lee1_mcp_demo-0.1.0.dist-info/WHEEL
lee1_mcp_demo-0.1.0.dist-info/entry_points.txt
lee1_mcp_demo-0.1.0.dist-info/RECORD
