Metadata-Version: 2.4
Name: lee1-mcp-demo
Version: 0.1.0
Summary: Add your description here
Author-email: "tao.li1" <tao.li1@okg.com>
Requires-Python: >=3.13
Requires-Dist: mcp[cli]>=1.10.1
